{"tag": "#92YP800CG", "name": "pho", "nameColor": "0xffff8afb", "trophies": 15366, "highestTrophies": 15372, "powerPlayPoints": 5, "highestPowerPlayPoints": 345, "expLevel": 95, "expPoints": 47633, "isQualifiedFromChampionshipChallenge": false, "3vs3Victories": 2754, "soloVictories": 45, "duoVictories": 71, "bestRoboRumbleTime": 0, "bestTimeAsBigBrawler": 0, "club": {"tag": "#8C9YGVC9", "name": "Grid North"}, "brawlers": [{"id": 16000000, "name": "SHELLY", "power": 10, "rank": 22, "trophies": 535, "highestTrophies": 636, "starPowers": [{"id": 23000135, "name": "Band-Aid"}, {"id": 23000076, "name": "Shell Shock"}], "gadgets": [], "points": 0}, {"id": 16000001, "name": "COLT", "power": 10, "rank": 21, "trophies": 578, "highestTrophies": 592, "starPowers": [{"id": 23000077, "name": "Slick Boots"}], "gadgets": [{"id": 23000273, "name": "Speedloader"}], "points": 0}, {"id": 16000002, "name": "BULL", "power": 7, "rank": 20, "trophies": 496, "highestTrophies": 503, "starPowers": [], "gadgets": [], "points": 867}, {"id": 16000003, "name": "BROCK", "power": 10, "rank": 21, "trophies": 587, "highestTrophies": 587, "starPowers": [{"id": 23000150, "name": "Rocket No. Four"}], "gadgets": [{"id": 23000245, "name": "Rocket Laces"}], "points": 0}, {"id": 16000004, "name": "RICO", "power": 8, "rank": 21, "trophies": 521, "highestTrophies": 557, "starPowers": [], "gadgets": [], "points": 550}, {"id": 16000006, "name": "BARLEY", "power": 7, "rank": 20, "trophies": 506, "highestTrophies": 512, "starPowers": [], "gadgets": [], "points": 679}, {"id": 16000007, "name": "JESSIE", "power": 10, "rank": 21, "trophies": 539, "highestTrophies": 591, "starPowers": [{"id": 23000083, "name": "Energize"}], "gadgets": [{"id": 23000251, "name": "Spark Plug"}], "points": 0}, {"id": 16000008, "name": "NITA", "power": 10, "rank": 21, "trophies": 527, "highestTrophies": 596, "starPowers": [{"id": 23000136, "name": "Hyper Bear"}, {"id": 23000084, "name": "Bear With Me"}], "gadgets": [], "points": 0}, {"id": 16000009, "name": "DYNAMIKE", "power": 8, "rank": 21, "trophies": 533, "highestTrophies": 563, "starPowers": [], "gadgets": [{"id": 23000258, "name": "Fidget Spinner"}], "points": 550}, {"id": 16000010, "name": "EL PRIMO", "power": 8, "rank": 21, "trophies": 510, "highestTrophies": 598, "starPowers": [], "gadgets": [{"id": 23000264, "name": "Suplex Supplement"}], "points": 433}, {"id": 16000011, "name": "MORTIS", "power": 7, "rank": 19, "trophies": 439, "highestTrophies": 461, "starPowers": [], "gadgets": [{"id": 23000265, "name": "Combo Spinner"}], "points": 745}, {"id": 16000012, "name": "CROW", "power": 6, "rank": 17, "trophies": 379, "highestTrophies": 387, "starPowers": [], "gadgets": [], "points": 57}, {"id": 16000013, "name": "POCO", "power": 7, "rank": 20, "trophies": 521, "highestTrophies": 539, "starPowers": [], "gadgets": [], "points": 874}, {"id": 16000014, "name": "BO", "power": 7, "rank": 20, "trophies": 545, "highestTrophies": 545, "starPowers": [], "gadgets": [], "points": 785}, {"id": 16000015, "name": "PIPER", "power": 7, "rank": 18, "trophies": 436, "highestTrophies": 436, "starPowers": [], "gadgets": [], "points": 404}, {"id": 16000016, "name": "PAM", "power": 7, "rank": 20, "trophies": 537, "highestTrophies": 537, "starPowers": [], "gadgets": [{"id": 23000257, "name": "Pulse Modulator"}], "points": 890}, {"id": 16000017, "name": "TARA", "power": 7, "rank": 20, "trophies": 498, "highestTrophies": 511, "starPowers": [], "gadgets": [{"id": 23000266, "name": "Psychic Enhancer"}], "points": 442}, {"id": 16000018, "name": "DARRYL", "power": 7, "rank": 21, "trophies": 534, "highestTrophies": 554, "starPowers": [], "gadgets": [], "points": 613}, {"id": 16000019, "name": "PENNY", "power": 8, "rank": 20, "trophies": 537, "highestTrophies": 537, "starPowers": [], "gadgets": [], "points": 550}, {"id": 16000020, "name": "FRANK", "power": 10, "rank": 21, "trophies": 525, "highestTrophies": 569, "starPowers": [{"id": 23000153, "name": "Sponge"}], "gadgets": [], "points": 0}, {"id": 16000021, "name": "GENE", "power": 7, "rank": 18, "trophies": 457, "highestTrophies": 457, "starPowers": [], "gadgets": [], "points": 585}, {"id": 16000022, "name": "TICK", "power": 7, "rank": 20, "trophies": 536, "highestTrophies": 549, "starPowers": [], "gadgets": [], "points": 558}, {"id": 16000024, "name": "ROSA", "power": 10, "rank": 21, "trophies": 591, "highestTrophies": 597, "starPowers": [{"id": 23000147, "name": "Thorny Gloves"}], "gadgets": [{"id": 23000242, "name": "Grow Light"}], "points": 0}, {"id": 16000025, "name": "CARL", "power": 7, "rank": 20, "trophies": 514, "highestTrophies": 520, "starPowers": [], "gadgets": [], "points": 601}, {"id": 16000026, "name": "BIBI", "power": 7, "rank": 20, "trophies": 521, "highestTrophies": 549, "starPowers": [], "gadgets": [], "points": 407}, {"id": 16000027, "name": "8-BIT", "power": 8, "rank": 21, "trophies": 571, "highestTrophies": 583, "starPowers": [], "gadgets": [], "points": 6}, {"id": 16000029, "name": "BEA", "power": 6, "rank": 20, "trophies": 531, "highestTrophies": 531, "starPowers": [], "gadgets": [], "points": 96}, {"id": 16000030, "name": "EMZ", "power": 7, "rank": 21, "trophies": 567, "highestTrophies": 573, "starPowers": [], "gadgets": [{"id": 23000274, "name": "Friendzoner"}], "points": 338}, {"id": 16000032, "name": "MAX", "power": 4, "rank": 18, "trophies": 406, "highestTrophies": 421, "starPowers": [], "gadgets": [], "points": 65}, {"id": 16000034, "name": "JACKY", "power": 5, "rank": 17, "trophies": 389, "highestTrophies": 389, "starPowers": [], "gadgets": [], "points": 64}], "coins": 908, "brawlpass": false, "tier": 29, "currentseason": 1, "coins_needed": 45790, "points_needed": 8791, "sp_needed": [5, 5], "gadgets_needed": [16, 16]}